cabina/__init__.py
cabina/_computed.py
cabina/_core.py
cabina/_environment.py
cabina/_future_value.py
cabina/_lazy_environment.py
cabina/_version.py
cabina/py.typed
cabina/errors/__init__.py
cabina/parsers/__init__.py
cabina-1.1.2.dist-info/LICENSE
cabina-1.1.2.dist-info/METADATA
cabina-1.1.2.dist-info/WHEEL
cabina-1.1.2.dist-info/top_level.txt
cabina-1.1.2.dist-info/RECORD
