Metadata-Version: 2.1
Name: cabina
Version: 1.1.2
Summary: Configuration with typed env vars
Home-page: https://github.com/tsv1/cabina
Author: Nikita Tsvetkov
Author-email: tsv1@fastmail.com
License: Apache-2.0
Classifier: License :: OSI Approved :: Apache Software License
Classifier: Programming Language :: Python :: 3.8
Classifier: Programming Language :: Python :: 3.9
Classifier: Programming Language :: Python :: 3.10
Classifier: Programming Language :: Python :: 3.11
Classifier: Programming Language :: Python :: 3.12
Classifier: Programming Language :: Python :: 3.13
Classifier: Typing :: Typed
Requires-Python: >=3.8
License-File: LICENSE
Requires-Dist: niltype<2.0,>=0.3
